quvis/__init__.py
quvis/api/__init__.py
quvis/api/fastapi_app.py
quvis/api/playground.py
quvis/api/visualizer.py
quvis/compiler/__init__.py
quvis/compiler/utils.py
quvis-0.27.1.dist-info/METADATA
quvis-0.27.1.dist-info/WHEEL
quvis-0.27.1.dist-info/RECORD
