Metadata-Version: 2.4
Name: quvis
Version: 0.27.1
Summary: Quvis - Quantum Circuit Visualization System
Author: Alejandro Gonzalvo Hidalgo
Author-email: alejandro@gonzalvo.org
Requires-Python: >=3.12,<4.0
Classifier: Programming Language :: Python :: 3
Classifier: Programming Language :: Python :: 3.12
Classifier: Programming Language :: Python :: 3.13
Classifier: Programming Language :: Python :: 3.14
Requires-Dist: fastapi (>=0.115.0,<0.116.0)
Requires-Dist: ipykernel (>=6.29.5,<7.0.0)
Requires-Dist: numpy (>=1.24.0,<2.0.0)
Requires-Dist: pillow (>=11.3.0,<12.0.0)
Requires-Dist: pydantic (>=2.10.0,<3.0.0)
Requires-Dist: qiskit (>=2.1.0,<3.0.0)
Requires-Dist: uvicorn[standard] (>=0.32.0,<0.33.0)
